cse40/__init__.py
ucsc_cse40-0.13.0.dist-info/METADATA
ucsc_cse40-0.13.0.dist-info/WHEEL
ucsc_cse40-0.13.0.dist-info/top_level.txt
ucsc_cse40-0.13.0.dist-info/RECORD
