Metadata-Version: 2.1
Name: ucsc-cse40
Version: 0.13.0
Summary: Dependencies for UCSC's CSE 40 - ML Basics: Data Analysis and Empirical Methods
Home-page: https://github.com/ucsc-cse-40/ucsc-cse40
Maintainer: Eriq Augustine
Maintainer-email: eaugusti@ucsc.edu
Keywords: grading
Classifier: Intended Audience :: Education
Classifier: License :: OSI Approved :: MIT License
Classifier: Programming Language :: Python :: 3.8
Requires-Python: >=3.8
Requires-Dist: jupyterlab>=3.5.0
Requires-Dist: matplotlib>=3.6.2
Requires-Dist: numpy>=1.22.3
Requires-Dist: pandas>=1.5.1
Requires-Dist: scikit-learn>=1.2.0
Requires-Dist: autograder-py==0.6.*
